{
  "generated_at": "2026-03-29T21:53:36.678062+00:00",
  "model_cycle": "2026-03-29T18:00:00+00:00",
  "grid_point": {
    "lat": 41.002677,
    "lon": -71.599534
  },
  "forecasts": [
    {
      "valid_time": "2026-03-29T18:00:00+00:00",
      "forecast_hour": 0,
      "height_ft": 2.0,
      "height_m": 0.6,
      "period_s": 3.1,
      "direction_deg": 213.0
    },
    {
      "valid_time": "2026-03-29T19:00:00+00:00",
      "forecast_hour": 1,
      "height_ft": 2.2,
      "height_m": 0.67,
      "period_s": 3.3,
      "direction_deg": 210.0
    },
    {
      "valid_time": "2026-03-29T20:00:00+00:00",
      "forecast_hour": 2,
      "height_ft": 2.6,
      "height_m": 0.78,
      "period_s": 3.7,
      "direction_deg": 213.0
    },
    {
      "valid_time": "2026-03-29T21:00:00+00:00",
      "forecast_hour": 3,
      "height_ft": 2.8,
      "height_m": 0.84,
      "period_s": 4.0,
      "direction_deg": 214.0
    },
    {
      "valid_time": "2026-03-29T22:00:00+00:00",
      "forecast_hour": 4,
      "height_ft": 2.9,
      "height_m": 0.88,
      "period_s": 4.2,
      "direction_deg": 214.0
    },
    {
      "valid_time": "2026-03-29T23:00:00+00:00",
      "forecast_hour": 5,
      "height_ft": 3.1,
      "height_m": 0.93,
      "period_s": 4.3,
      "direction_deg": 213.0
    },
    {
      "valid_time": "2026-03-30T00:00:00+00:00",
      "forecast_hour": 6,
      "height_ft": 3.6,
      "height_m": 1.09,
      "period_s": 4.6,
      "direction_deg": 211.0
    },
    {
      "valid_time": "2026-03-30T01:00:00+00:00",
      "forecast_hour": 7,
      "height_ft": 4.2,
      "height_m": 1.27,
      "period_s": 5.0,
      "direction_deg": 210.0
    },
    {
      "valid_time": "2026-03-30T02:00:00+00:00",
      "forecast_hour": 8,
      "height_ft": 4.8,
      "height_m": 1.47,
      "period_s": 5.3,
      "direction_deg": 211.0
    },
    {
      "valid_time": "2026-03-30T03:00:00+00:00",
      "forecast_hour": 9,
      "height_ft": 5.3,
      "height_m": 1.62,
      "period_s": 5.6,
      "direction_deg": 211.0
    },
    {
      "valid_time": "2026-03-30T04:00:00+00:00",
      "forecast_hour": 10,
      "height_ft": 5.4,
      "height_m": 1.65,
      "period_s": 5.9,
      "direction_deg": 212.0
    },
    {
      "valid_time": "2026-03-30T05:00:00+00:00",
      "forecast_hour": 11,
      "height_ft": 5.2,
      "height_m": 1.6,
      "period_s": 6.0,
      "direction_deg": 212.0
    },
    {
      "valid_time": "2026-03-30T06:00:00+00:00",
      "forecast_hour": 12,
      "height_ft": 5.0,
      "height_m": 1.51,
      "period_s": 6.0,
      "direction_deg": 211.0
    },
    {
      "valid_time": "2026-03-30T07:00:00+00:00",
      "forecast_hour": 13,
      "height_ft": 4.9,
      "height_m": 1.48,
      "period_s": 6.0,
      "direction_deg": 211.0
    },
    {
      "valid_time": "2026-03-30T08:00:00+00:00",
      "forecast_hour": 14,
      "height_ft": 5.2,
      "height_m": 1.58,
      "period_s": 5.9,
      "direction_deg": 211.0
    },
    {
      "valid_time": "2026-03-30T09:00:00+00:00",
      "forecast_hour": 15,
      "height_ft": 5.5,
      "height_m": 1.69,
      "period_s": 6.0,
      "direction_deg": 210.0
    },
    {
      "valid_time": "2026-03-30T10:00:00+00:00",
      "forecast_hour": 16,
      "height_ft": 5.5,
      "height_m": 1.67,
      "period_s": 6.0,
      "direction_deg": 210.0
    },
    {
      "valid_time": "2026-03-30T11:00:00+00:00",
      "forecast_hour": 17,
      "height_ft": 6.0,
      "height_m": 1.82,
      "period_s": 6.3,
      "direction_deg": 212.0
    },
    {
      "valid_time": "2026-03-30T12:00:00+00:00",
      "forecast_hour": 18,
      "height_ft": 6.3,
      "height_m": 1.92,
      "period_s": 6.8,
      "direction_deg": 212.0
    },
    {
      "valid_time": "2026-03-30T13:00:00+00:00",
      "forecast_hour": 19,
      "height_ft": 6.2,
      "height_m": 1.9,
      "period_s": 6.9,
      "direction_deg": 210.0
    },
    {
      "valid_time": "2026-03-30T14:00:00+00:00",
      "forecast_hour": 20,
      "height_ft": 6.0,
      "height_m": 1.84,
      "period_s": 6.9,
      "direction_deg": 208.0
    },
    {
      "valid_time": "2026-03-30T15:00:00+00:00",
      "forecast_hour": 21,
      "height_ft": 6.3,
      "height_m": 1.91,
      "period_s": 6.8,
      "direction_deg": 208.0
    },
    {
      "valid_time": "2026-03-30T16:00:00+00:00",
      "forecast_hour": 22,
      "height_ft": 6.4,
      "height_m": 1.96,
      "period_s": 6.8,
      "direction_deg": 209.0
    },
    {
      "valid_time": "2026-03-30T17:00:00+00:00",
      "forecast_hour": 23,
      "height_ft": 7.1,
      "height_m": 2.17,
      "period_s": 6.9,
      "direction_deg": 210.0
    },
    {
      "valid_time": "2026-03-30T18:00:00+00:00",
      "forecast_hour": 24,
      "height_ft": 7.4,
      "height_m": 2.27,
      "period_s": 7.2,
      "direction_deg": 208.0
    },
    {
      "valid_time": "2026-03-30T19:00:00+00:00",
      "forecast_hour": 25,
      "height_ft": 7.5,
      "height_m": 2.29,
      "period_s": 7.2,
      "direction_deg": 208.0
    },
    {
      "valid_time": "2026-03-30T20:00:00+00:00",
      "forecast_hour": 26,
      "height_ft": 7.6,
      "height_m": 2.31,
      "period_s": 7.3,
      "direction_deg": 207.0
    },
    {
      "valid_time": "2026-03-30T21:00:00+00:00",
      "forecast_hour": 27,
      "height_ft": 7.6,
      "height_m": 2.33,
      "period_s": 7.4,
      "direction_deg": 207.0
    },
    {
      "valid_time": "2026-03-30T22:00:00+00:00",
      "forecast_hour": 28,
      "height_ft": 7.6,
      "height_m": 2.32,
      "period_s": 7.6,
      "direction_deg": 207.0
    },
    {
      "valid_time": "2026-03-30T23:00:00+00:00",
      "forecast_hour": 29,
      "height_ft": 7.5,
      "height_m": 2.3,
      "period_s": 7.6,
      "direction_deg": 202.0
    },
    {
      "valid_time": "2026-03-31T00:00:00+00:00",
      "forecast_hour": 30,
      "height_ft": 7.4,
      "height_m": 2.26,
      "period_s": 7.7,
      "direction_deg": 201.0
    },
    {
      "valid_time": "2026-03-31T01:00:00+00:00",
      "forecast_hour": 31,
      "height_ft": 7.3,
      "height_m": 2.21,
      "period_s": 7.6,
      "direction_deg": 200.0
    },
    {
      "valid_time": "2026-03-31T02:00:00+00:00",
      "forecast_hour": 32,
      "height_ft": 6.9,
      "height_m": 2.09,
      "period_s": 7.6,
      "direction_deg": 198.0
    },
    {
      "valid_time": "2026-03-31T03:00:00+00:00",
      "forecast_hour": 33,
      "height_ft": 6.6,
      "height_m": 2.01,
      "period_s": 7.6,
      "direction_deg": 202.0
    },
    {
      "valid_time": "2026-03-31T04:00:00+00:00",
      "forecast_hour": 34,
      "height_ft": 6.4,
      "height_m": 1.95,
      "period_s": 7.5,
      "direction_deg": 201.0
    },
    {
      "valid_time": "2026-03-31T05:00:00+00:00",
      "forecast_hour": 35,
      "height_ft": 6.4,
      "height_m": 1.94,
      "period_s": 7.5,
      "direction_deg": 200.0
    },
    {
      "valid_time": "2026-03-31T06:00:00+00:00",
      "forecast_hour": 36,
      "height_ft": 6.2,
      "height_m": 1.9,
      "period_s": 7.4,
      "direction_deg": 198.0
    },
    {
      "valid_time": "2026-03-31T07:00:00+00:00",
      "forecast_hour": 37,
      "height_ft": 6.1,
      "height_m": 1.86,
      "period_s": 7.4,
      "direction_deg": 197.0
    },
    {
      "valid_time": "2026-03-31T08:00:00+00:00",
      "forecast_hour": 38,
      "height_ft": 5.9,
      "height_m": 1.81,
      "period_s": 7.4,
      "direction_deg": 195.0
    },
    {
      "valid_time": "2026-03-31T09:00:00+00:00",
      "forecast_hour": 39,
      "height_ft": 5.9,
      "height_m": 1.79,
      "period_s": 7.5,
      "direction_deg": 195.0
    },
    {
      "valid_time": "2026-03-31T10:00:00+00:00",
      "forecast_hour": 40,
      "height_ft": 6.0,
      "height_m": 1.83,
      "period_s": 7.7,
      "direction_deg": 189.0
    },
    {
      "valid_time": "2026-03-31T11:00:00+00:00",
      "forecast_hour": 41,
      "height_ft": 6.2,
      "height_m": 1.9,
      "period_s": 7.8,
      "direction_deg": 190.0
    },
    {
      "valid_time": "2026-03-31T12:00:00+00:00",
      "forecast_hour": 42,
      "height_ft": 6.5,
      "height_m": 1.97,
      "period_s": 7.8,
      "direction_deg": 190.0
    },
    {
      "valid_time": "2026-03-31T13:00:00+00:00",
      "forecast_hour": 43,
      "height_ft": 6.6,
      "height_m": 2.02,
      "period_s": 7.8,
      "direction_deg": 190.0
    },
    {
      "valid_time": "2026-03-31T14:00:00+00:00",
      "forecast_hour": 44,
      "height_ft": 6.5,
      "height_m": 1.99,
      "period_s": 7.8,
      "direction_deg": 191.0
    },
    {
      "valid_time": "2026-03-31T15:00:00+00:00",
      "forecast_hour": 45,
      "height_ft": 6.5,
      "height_m": 1.98,
      "period_s": 7.8,
      "direction_deg": 191.0
    },
    {
      "valid_time": "2026-03-31T16:00:00+00:00",
      "forecast_hour": 46,
      "height_ft": 6.5,
      "height_m": 1.99,
      "period_s": 7.8,
      "direction_deg": 192.0
    },
    {
      "valid_time": "2026-03-31T17:00:00+00:00",
      "forecast_hour": 47,
      "height_ft": 6.6,
      "height_m": 2.0,
      "period_s": 7.7,
      "direction_deg": 192.0
    },
    {
      "valid_time": "2026-03-31T18:00:00+00:00",
      "forecast_hour": 48,
      "height_ft": 6.4,
      "height_m": 1.94,
      "period_s": 7.7,
      "direction_deg": 192.0
    },
    {
      "valid_time": "2026-03-31T19:00:00+00:00",
      "forecast_hour": 49,
      "height_ft": 6.1,
      "height_m": 1.87,
      "period_s": 7.7,
      "direction_deg": 192.0
    },
    {
      "valid_time": "2026-03-31T20:00:00+00:00",
      "forecast_hour": 50,
      "height_ft": 5.9,
      "height_m": 1.8,
      "period_s": 7.7,
      "direction_deg": 192.0
    },
    {
      "valid_time": "2026-03-31T21:00:00+00:00",
      "forecast_hour": 51,
      "height_ft": 5.8,
      "height_m": 1.76,
      "period_s": 7.7,
      "direction_deg": 192.0
    },
    {
      "valid_time": "2026-03-31T22:00:00+00:00",
      "forecast_hour": 52,
      "height_ft": 5.7,
      "height_m": 1.75,
      "period_s": 7.7,
      "direction_deg": 192.0
    },
    {
      "valid_time": "2026-03-31T23:00:00+00:00",
      "forecast_hour": 53,
      "height_ft": 5.7,
      "height_m": 1.75,
      "period_s": 7.6,
      "direction_deg": 192.0
    },
    {
      "valid_time": "2026-04-01T00:00:00+00:00",
      "forecast_hour": 54,
      "height_ft": 5.8,
      "height_m": 1.78,
      "period_s": 7.6,
      "direction_deg": 196.0
    },
    {
      "valid_time": "2026-04-01T01:00:00+00:00",
      "forecast_hour": 55,
      "height_ft": 5.9,
      "height_m": 1.79,
      "period_s": 7.6,
      "direction_deg": 196.0
    },
    {
      "valid_time": "2026-04-01T02:00:00+00:00",
      "forecast_hour": 56,
      "height_ft": 6.2,
      "height_m": 1.88,
      "period_s": 7.5,
      "direction_deg": 196.0
    },
    {
      "valid_time": "2026-04-01T03:00:00+00:00",
      "forecast_hour": 57,
      "height_ft": 6.4,
      "height_m": 1.96,
      "period_s": 7.5,
      "direction_deg": 196.0
    },
    {
      "valid_time": "2026-04-01T04:00:00+00:00",
      "forecast_hour": 58,
      "height_ft": 6.8,
      "height_m": 2.07,
      "period_s": 7.4,
      "direction_deg": 197.0
    },
    {
      "valid_time": "2026-04-01T05:00:00+00:00",
      "forecast_hour": 59,
      "height_ft": 7.4,
      "height_m": 2.27,
      "period_s": 7.3,
      "direction_deg": 198.0
    },
    {
      "valid_time": "2026-04-01T06:00:00+00:00",
      "forecast_hour": 60,
      "height_ft": 7.7,
      "height_m": 2.34,
      "period_s": 7.4,
      "direction_deg": 198.0
    },
    {
      "valid_time": "2026-04-01T07:00:00+00:00",
      "forecast_hour": 61,
      "height_ft": 7.8,
      "height_m": 2.38,
      "period_s": 7.5,
      "direction_deg": 198.0
    },
    {
      "valid_time": "2026-04-01T08:00:00+00:00",
      "forecast_hour": 62,
      "height_ft": 7.8,
      "height_m": 2.39,
      "period_s": 7.6,
      "direction_deg": 199.0
    },
    {
      "valid_time": "2026-04-01T09:00:00+00:00",
      "forecast_hour": 63,
      "height_ft": 7.8,
      "height_m": 2.38,
      "period_s": 7.7,
      "direction_deg": 193.0
    },
    {
      "valid_time": "2026-04-01T10:00:00+00:00",
      "forecast_hour": 64,
      "height_ft": 7.9,
      "height_m": 2.41,
      "period_s": 7.8,
      "direction_deg": 194.0
    },
    {
      "valid_time": "2026-04-01T11:00:00+00:00",
      "forecast_hour": 65,
      "height_ft": 7.8,
      "height_m": 2.37,
      "period_s": 7.8,
      "direction_deg": 193.0
    },
    {
      "valid_time": "2026-04-01T12:00:00+00:00",
      "forecast_hour": 66,
      "height_ft": 7.6,
      "height_m": 2.32,
      "period_s": 7.9,
      "direction_deg": 192.0
    },
    {
      "valid_time": "2026-04-01T13:00:00+00:00",
      "forecast_hour": 67,
      "height_ft": 7.5,
      "height_m": 2.3,
      "period_s": 7.9,
      "direction_deg": 192.0
    },
    {
      "valid_time": "2026-04-01T14:00:00+00:00",
      "forecast_hour": 68,
      "height_ft": 7.3,
      "height_m": 2.22,
      "period_s": 7.9,
      "direction_deg": 191.0
    },
    {
      "valid_time": "2026-04-01T15:00:00+00:00",
      "forecast_hour": 69,
      "height_ft": 7.2,
      "height_m": 2.18,
      "period_s": 7.9,
      "direction_deg": 190.0
    },
    {
      "valid_time": "2026-04-01T16:00:00+00:00",
      "forecast_hour": 70,
      "height_ft": 7.2,
      "height_m": 2.19,
      "period_s": 8.0,
      "direction_deg": 191.0
    },
    {
      "valid_time": "2026-04-01T17:00:00+00:00",
      "forecast_hour": 71,
      "height_ft": 7.3,
      "height_m": 2.22,
      "period_s": 8.0,
      "direction_deg": 191.0
    },
    {
      "valid_time": "2026-04-01T18:00:00+00:00",
      "forecast_hour": 72,
      "height_ft": 7.1,
      "height_m": 2.16,
      "period_s": 8.0,
      "direction_deg": 190.0
    },
    {
      "valid_time": "2026-04-01T19:00:00+00:00",
      "forecast_hour": 73,
      "height_ft": 6.9,
      "height_m": 2.09,
      "period_s": 8.0,
      "direction_deg": 190.0
    },
    {
      "valid_time": "2026-04-01T20:00:00+00:00",
      "forecast_hour": 74,
      "height_ft": 6.7,
      "height_m": 2.03,
      "period_s": 7.9,
      "direction_deg": 189.0
    },
    {
      "valid_time": "2026-04-01T21:00:00+00:00",
      "forecast_hour": 75,
      "height_ft": 6.5,
      "height_m": 1.97,
      "period_s": 7.9,
      "direction_deg": 189.0
    },
    {
      "valid_time": "2026-04-01T22:00:00+00:00",
      "forecast_hour": 76,
      "height_ft": 6.3,
      "height_m": 1.93,
      "period_s": 7.8,
      "direction_deg": 188.0
    },
    {
      "valid_time": "2026-04-01T23:00:00+00:00",
      "forecast_hour": 77,
      "height_ft": 6.2,
      "height_m": 1.9,
      "period_s": 7.8,
      "direction_deg": 187.0
    },
    {
      "valid_time": "2026-04-02T00:00:00+00:00",
      "forecast_hour": 78,
      "height_ft": 6.1,
      "height_m": 1.85,
      "period_s": 7.8,
      "direction_deg": 186.0
    },
    {
      "valid_time": "2026-04-02T01:00:00+00:00",
      "forecast_hour": 79,
      "height_ft": 5.9,
      "height_m": 1.8,
      "period_s": 7.7,
      "direction_deg": 186.0
    },
    {
      "valid_time": "2026-04-02T02:00:00+00:00",
      "forecast_hour": 80,
      "height_ft": 5.8,
      "height_m": 1.78,
      "period_s": 7.7,
      "direction_deg": 185.0
    },
    {
      "valid_time": "2026-04-02T03:00:00+00:00",
      "forecast_hour": 81,
      "height_ft": 5.7,
      "height_m": 1.74,
      "period_s": 7.6,
      "direction_deg": 184.0
    },
    {
      "valid_time": "2026-04-02T04:00:00+00:00",
      "forecast_hour": 82,
      "height_ft": 5.5,
      "height_m": 1.68,
      "period_s": 7.6,
      "direction_deg": 188.0
    },
    {
      "valid_time": "2026-04-02T05:00:00+00:00",
      "forecast_hour": 83,
      "height_ft": 5.3,
      "height_m": 1.62,
      "period_s": 7.5,
      "direction_deg": 188.0
    },
    {
      "valid_time": "2026-04-02T06:00:00+00:00",
      "forecast_hour": 84,
      "height_ft": 5.1,
      "height_m": 1.56,
      "period_s": 7.4,
      "direction_deg": 187.0
    },
    {
      "valid_time": "2026-04-02T07:00:00+00:00",
      "forecast_hour": 85,
      "height_ft": 5.0,
      "height_m": 1.51,
      "period_s": 7.4,
      "direction_deg": 186.0
    },
    {
      "valid_time": "2026-04-02T08:00:00+00:00",
      "forecast_hour": 86,
      "height_ft": 4.8,
      "height_m": 1.46,
      "period_s": 7.4,
      "direction_deg": 185.0
    },
    {
      "valid_time": "2026-04-02T09:00:00+00:00",
      "forecast_hour": 87,
      "height_ft": 4.6,
      "height_m": 1.41,
      "period_s": 7.3,
      "direction_deg": 184.0
    },
    {
      "valid_time": "2026-04-02T10:00:00+00:00",
      "forecast_hour": 88,
      "height_ft": 4.5,
      "height_m": 1.36,
      "period_s": 7.3,
      "direction_deg": 183.0
    },
    {
      "valid_time": "2026-04-02T11:00:00+00:00",
      "forecast_hour": 89,
      "height_ft": 4.4,
      "height_m": 1.33,
      "period_s": 7.2,
      "direction_deg": 182.0
    },
    {
      "valid_time": "2026-04-02T12:00:00+00:00",
      "forecast_hour": 90,
      "height_ft": 4.4,
      "height_m": 1.33,
      "period_s": 7.1,
      "direction_deg": 185.0
    },
    {
      "valid_time": "2026-04-02T13:00:00+00:00",
      "forecast_hour": 91,
      "height_ft": 4.4,
      "height_m": 1.35,
      "period_s": 7.0,
      "direction_deg": 185.0
    },
    {
      "valid_time": "2026-04-02T14:00:00+00:00",
      "forecast_hour": 92,
      "height_ft": 4.5,
      "height_m": 1.36,
      "period_s": 7.0,
      "direction_deg": 184.0
    },
    {
      "valid_time": "2026-04-02T15:00:00+00:00",
      "forecast_hour": 93,
      "height_ft": 4.4,
      "height_m": 1.33,
      "period_s": 6.9,
      "direction_deg": 184.0
    }
  ]
}